miraie_ac/__init__.py
miraie_ac/broker.py
miraie_ac/constants.py
miraie_ac/device.py
miraie_ac/enums.py
miraie_ac/home.py
miraie_ac/hub.py
miraie_ac/logger.py
miraie_ac/topic.py
miraie_ac/user.py
miraie_ac/utils.py
miraie_ac-1.1.1.dist-info/LICENSE
miraie_ac-1.1.1.dist-info/METADATA
miraie_ac-1.1.1.dist-info/WHEEL
miraie_ac-1.1.1.dist-info/RECORD
